LICENSE
MANIFEST.in
README.md
setup.py
trix/__init__.py
trix/version.py
trix.egg-info/PKG-INFO
trix.egg-info/SOURCES.txt
trix.egg-info/dependency_links.txt
trix.egg-info/not-zip-safe
trix.egg-info/requires.txt
trix.egg-info/top_level.txt
trix/project/__init__.py
trix/project/settingsproxy.py
trix/project/default/__init__.py
trix/project/default/default_urls.py
trix/project/default/settings.py
trix/project/default/templatecontext.py
trix/project/develop/__init__.py
trix/project/develop/developtasks.py
trix/project/develop/urls.py
trix/project/develop/dumps/__init__.py
trix/project/develop/dumps/dev/__init__.py
trix/project/develop/dumps/dev/data.py
trix/project/develop/dumps/dev/import_helper.py
trix/project/develop/settings/__init__.py
trix/project/develop/settings/common.py
trix/project/develop/settings/develop.py
trix/project/develop/settings/test.py
trix/project/develop/testhelpers/__init__.py
trix/project/develop/testhelpers/login.py
trix/project/develop/testhelpers/user.py
trix/project/production/__init__.py
trix/project/production/settings.py
trix/project/production/urls.py
trix/project/production/wsgi.py
trix/trix_admin/__init__.py
trix/trix_admin/cradmin.py
trix/trix_admin/css_icon_map.py
trix/trix_admin/editor_widget.py
trix/trix_admin/formfields.py
trix/trix_admin/models.py
trix/trix_admin/locale/nb/LC_MESSAGES/django.mo
trix/trix_admin/locale/nb/LC_MESSAGES/django.po
trix/trix_admin/management/__init__.py
trix/trix_admin/management/commands/__init__.py
trix/trix_admin/management/commands/generatetestdata.py
trix/trix_admin/static/trix_admin/plain_es6/commentEditor.js
trix/trix_admin/static/trix_admin/plain_es6/cookie.js
trix/trix_admin/static/trix_admin/plain_es6/datepicker.js
trix/trix_admin/static/trix_admin/plain_es6/webcomponent_utils.js
trix/trix_admin/templates/cradmin_legacy/base.django.html
trix/trix_admin/templates/cradmin_legacy/standalone-base.django.html
trix/trix_admin/templates/cradmin_legacy/layouts/standalone/focused.django.html
trix/trix_admin/templates/cradmin_legacy/pagepreview/includes/pagepreview-fullsize-iframe-wrapper.django.html
