Metadata-Version: 2.1
Name: trix
Version: 4.1.1
Summary: Next generation Trix. Detailed task control and statistics app for better learning outcome.
Home-page: https://github.com/devilry/trix2
Author: Tor Johansen, Espen Angell Kristiansen, Jonas Sandbekk
Author-email: tor@appresso.no, espen@appresso.no, jonassandbekk@gmail.com
License: BSD
Classifier: Development Status :: 4 - Beta
Classifier: Environment :: Web Environment
Classifier: Framework :: Django
Classifier: Framework :: Django :: 3.2
Classifier: Intended Audience :: Developers
Classifier: License :: OSI Approved
Classifier: Operating System :: OS Independent
Classifier: Programming Language :: Python
License-File: LICENSE
Requires-Dist: setuptools
Requires-Dist: Django==4.2.*
Requires-Dist: django-crispy-forms<=1.14,>=1.13
Requires-Dist: Markdown>=3.4.1
Requires-Dist: PyYAML>=6.0
Requires-Dist: django-extensions
Requires-Dist: cradmin_legacy>=5.0.0
Requires-Dist: gunicorn
